L4T2.v
// 32-bit Adder that adds a 4-bit value to a 32-bit value
// This module is purely combinational

module adder_32_4 (
    input  [31:0] A,        // 32-bit input (current counter value)
    input  [3:0]  B,        // 4-bit input number
    output [31:0] Sum       // 32-bit output (A + B)
);

    // Zero-extend B to 32 bits and add
    assign Sum = A + {{28{1'b0}}, B};

endmodule

// 32-bit Counter Register
// Updates its value on the positive edge of the clock

module counter32 (
    input clk,
    input reset,
    input [31:0] next_value,   // Value to be loaded into counter
    output reg [31:0] count
);

    always @(posedge clk or posedge reset) begin
        if (reset)
            count <= 32'b0;     // Reset counter to zero
        else
            count <= next_value; // Load new value
    end

endmodule

// Top module connecting adder and counter using instantiation

module counter_with_adder (
    input clk,
    input reset,
    input [3:0] add_value,    // 4-bit number added each clock
    output [31:0] count
);

    wire [31:0] adder_out;    // Wire connecting adder to counter

    // Instantiate Adder
    adder_32_4 ADDER (
        .A(count),            // Current counter value
        .B(add_value),        // 4-bit input
        .Sum(adder_out)       // Output to counter
    );

    // Instantiate Counter
    counter32 COUNTER (
        .clk(clk),
        .reset(reset),
        .next_value(adder_out),
        .count(count)
    );

endmodule

L4T2_tb.v
`timescale 1ns / 1ps

module counter_with_adder_tb;

    reg clk;
    reg reset;
    reg [3:0] add_value;
    wire [31:0] count;

    // Instantiate the top module
    counter_with_adder uut (
        .clk(clk),
        .reset(reset),
        .add_value(add_value),
        .count(count)
    );

    // Clock generation: 10ns period
    always #5 clk = ~clk;

    initial begin
        // Dump waveform for GTKWave
        $dumpfile("counter_with_adder.vcd");
        $dumpvars(0, counter_with_adder_tb);

        // Initialize signals
        clk = 0;
        reset = 1;
        add_value = 4'd0;

        // Apply reset
        #10 reset = 0;

        // Add 3 every clock
        add_value = 4'd3;
        #40;

        // Change increment value to 5
        add_value = 4'd5;
        #40;

        // Reset again
        reset = 1;
        #10 reset = 0;

        // Add 2 every clock
        add_value = 4'd2;
        #30;

        $finish;
    end

endmodule

counter_with_adder.vcd
$date
	Fri Feb  6 10:43:41 2026
$end
$version
	Icarus Verilog
$end
$timescale
	1ps
$end
$scope module counter_with_adder_tb $end
$var wire 32 ! count [31:0] $end
$var reg 4 " add_value [3:0] $end
$var reg 1 # clk $end
$var reg 1 $ reset $end
$scope module uut $end
$var wire 4 % add_value [3:0] $end
$var wire 1 # clk $end
$var wire 1 $ reset $end
$var wire 32 & count [31:0] $end
$var wire 32 ' adder_out [31:0] $end
$scope module ADDER $end
$var wire 4 ( B [3:0] $end
$var wire 32 ) Sum [31:0] $end
$var wire 32 * A [31:0] $end
$upscope $end
$scope module COUNTER $end
$var wire 1 # clk $end
$var wire 32 + next_value [31:0] $end
$var wire 1 $ reset $end
$var reg 32 , count [31:0] $end
$upscope $end
$upscope $end
$upscope $end
$enddefinitions $end
#0
$dumpvars
b0 ,
b0 +
b0 *
b0 )
b0 (
b0 '
b0 &
b0 %
1$
0#
b0 "
b0 !
$end
#5000
1#
#10000
0#
b11 '
b11 )
b11 +
b11 "
b11 %
b11 (
0$
#15000
b110 '
b110 )
b110 +
b11 !
b11 &
b11 *
b11 ,
1#
#20000
0#
#25000
b1001 '
b1001 )
b1001 +
b110 !
b110 &
b110 *
b110 ,
1#
#30000
0#
#35000
b1100 '
b1100 )
b1100 +
b1001 !
b1001 &
b1001 *
b1001 ,
1#
#40000
0#
#45000
b1111 '
b1111 )
b1111 +
b1100 !
b1100 &
b1100 *
b1100 ,
1#
#50000
0#
b10001 '
b10001 )
b10001 +
b101 "
b101 %
b101 (
#55000
b10110 '
b10110 )
b10110 +
b10001 !
b10001 &
b10001 *
b10001 ,
1#
#60000
0#
#65000
b11011 '
b11011 )
b11011 +
b10110 !
b10110 &
b10110 *
b10110 ,
1#
#70000
0#
#75000
b100000 '
b100000 )
b100000 +
b11011 !
b11011 &
b11011 *
b11011 ,
1#
#80000
0#
#85000
b100101 '
b100101 )
b100101 +
b100000 !
b100000 &
b100000 *
b100000 ,
1#
#90000
b101 '
b101 )
b101 +
b0 !
b0 &
b0 *
b0 ,
0#
1$
#95000
1#
#100000
0#
b10 '
b10 )
b10 +
b10 "
b10 %
b10 (
0$
#105000
b100 '
b100 )
b100 +
b10 !
b10 &
b10 *
b10 ,
1#
#110000
0#
#115000
b110 '
b110 )
b110 +
b100 !
b100 &
b100 *
b100 ,
1#
#120000
0#
#125000
b1000 '
b1000 )
b1000 +
b110 !
b110 &
b110 *
b110 ,
1#
