processor.v
module pc(input clk, input reset, input [31:0] next_pc, output reg [31:0] pc_out);
always @(posedge clk or posedge reset) begin
    if (reset)
        pc_out <= 0;
    else
        pc_out <= next_pc;
end
endmodule

module instruction_memory(input [31:0] addr, output [31:0] instruction);

reg [31:0] mem [0:255];

initial begin
    $readmemb("instructions.mem", mem); // load binary instructions
end

assign instruction = mem[addr[9:2]]; // word aligned

endmodule

module register_file(
    input clk,
    input regWrite,
    input [4:0] rs1, rs2, rd,
    input [31:0] writeData,
    output [31:0] readData1, readData2
);

reg [31:0] regs [0:31];

assign readData1 = regs[rs1];
assign readData2 = regs[rs2];

always @(posedge clk) begin
    if (regWrite && rd != 0)
        regs[rd] <= writeData;
end

endmodule

module alu(
    input [31:0] a, b,
    input [3:0] alu_control,
    output reg [31:0] result,
    output zero
);

always @(*) begin
    case (alu_control)
        4'b0000: result = a & b;   // AND
        4'b0001: result = a | b;   // OR
        4'b0010: result = a + b;   // ADD
        4'b0110: result = a - b;   // SUB
        default: result = 0;
    endcase
end

assign zero = (result == 0);

endmodule

module data_memory(
    input clk,
    input memRead, memWrite,
    input [31:0] addr,
    input [31:0] writeData,
    output [31:0] readData
);

reg [31:0] mem [0:4095]; // 4096 words = 16KB

assign readData = (memRead) ? mem[addr[13:2]] : 0;

always @(posedge clk) begin
    if (memWrite)
        mem[addr[13:2]] <= writeData;
end

endmodule

module control_unit(
    input [6:0] opcode,
    output reg RegWrite, MemRead, MemWrite, ALUSrc, Branch,
    output reg [1:0] ALUOp
);

always @(*) begin
    case (opcode)
        7'b0110011: begin // R-type
            RegWrite = 1; MemRead = 0; MemWrite = 0;
            ALUSrc = 0; Branch = 0; ALUOp = 2'b10;
        end
        7'b0000011: begin // lw
            RegWrite = 1; MemRead = 1; MemWrite = 0;
            ALUSrc = 1; Branch = 0; ALUOp = 2'b00;
        end
        7'b0100011: begin // sw
            RegWrite = 0; MemRead = 0; MemWrite = 1;
            ALUSrc = 1; Branch = 0; ALUOp = 2'b00;
        end
        7'b1100011: begin // beq
            RegWrite = 0; MemRead = 0; MemWrite = 0;
            ALUSrc = 0; Branch = 1; ALUOp = 2'b01;
        end
        default: begin
            RegWrite = 0; MemRead = 0; MemWrite = 0;
            ALUSrc = 0; Branch = 0; ALUOp = 2'b00;
        end
    endcase
end

endmodule

module alu_control(
    input [1:0] ALUOp,
    input [6:0] funct7,
    input [2:0] funct3,
    output reg [3:0] alu_ctrl
);

always @(*) begin
    case (ALUOp)
        2'b00: alu_ctrl = 4'b0010; // ADD (lw, sw)
        2'b01: alu_ctrl = 4'b0110; // SUB (beq)
        2'b10: begin
            case ({funct7, funct3})
                {7'b0000000,3'b000}: alu_ctrl = 4'b0010; // add
                {7'b0100000,3'b000}: alu_ctrl = 4'b0110; // sub
                {7'b0000000,3'b111}: alu_ctrl = 4'b0000; // and
                {7'b0000000,3'b110}: alu_ctrl = 4'b0001; // or
                default: alu_ctrl = 4'b0000;
            endcase
        end
    endcase
end

endmodule

module imm_gen(input [31:0] instr, output reg [31:0] imm);

always @(*) begin
    case (instr[6:0])
        7'b0000011: // lw (I-type)
            imm = {{20{instr[31]}}, instr[31:20]};
        7'b0100011: // sw (S-type)
            imm = {{20{instr[31]}}, instr[31:25], instr[11:7]};
        7'b1100011: // beq (B-type)
            imm = {{19{instr[31]}}, instr[31], instr[7],
                   instr[30:25], instr[11:8], 1'b0};
        default:
            imm = 0;
    endcase
end

endmodule

module risc_v_single_cycle(input clk, input reset);

wire [31:0] pc, next_pc, instruction;
wire [31:0] readData1, readData2, writeData, imm;
wire [31:0] alu_in2, alu_result, mem_data;
wire zero;

wire RegWrite, MemRead, MemWrite, ALUSrc, Branch;
wire [1:0] ALUOp;
wire [3:0] alu_ctrl;

// PC
pc pc0(clk, reset, next_pc, pc);

// Instruction Memory
instruction_memory im(pc, instruction);

// Control Unit
control_unit cu(instruction[6:0], RegWrite, MemRead, MemWrite, ALUSrc, Branch, ALUOp);

// Register File
register_file rf(clk, RegWrite, instruction[19:15], instruction[24:20],
                 instruction[11:7], writeData, readData1, readData2);

// Immediate Generator
imm_gen ig(instruction, imm);

// ALU Control
alu_control ac(ALUOp, instruction[31:25], instruction[14:12], alu_ctrl);

// ALU Input MUX
assign alu_in2 = (ALUSrc) ? imm : readData2;

// ALU
alu alu0(readData1, alu_in2, alu_ctrl, alu_result, zero);

// Data Memory
data_memory dm(clk, MemRead, MemWrite, alu_result, readData2, mem_data);

// Write Back MUX
assign writeData = (MemRead) ? mem_data : alu_result;

// PC Logic
assign next_pc = (Branch && zero) ? pc + imm : pc + 4;

endmodule

module tb;

reg clk = 0;
reg reset = 1;

risc_v_single_cycle uut(clk, reset);

always #5 clk = ~clk;

initial begin
    $dumpfile("dump.vcd");
    $dumpvars(0, tb);

    #10 reset = 0;

    #200 $finish;
end

endmodule

dump.vcd
$date
	Fri Apr 10 09:03:42 2026
$end
$version
	Icarus Verilog
$end
$timescale
	1s
$end
$scope module tb $end
$var reg 1 ! clk $end
$var reg 1 " reset $end
$scope module uut $end
$var wire 1 ! clk $end
$var wire 1 " reset $end
$var wire 1 # zero $end
$var wire 32 $ writeData [31:0] $end
$var wire 32 % readData2 [31:0] $end
$var wire 32 & readData1 [31:0] $end
$var wire 32 ' pc [31:0] $end
$var wire 32 ( next_pc [31:0] $end
$var wire 32 ) mem_data [31:0] $end
$var wire 32 * instruction [31:0] $end
$var wire 32 + imm [31:0] $end
$var wire 32 , alu_result [31:0] $end
$var wire 32 - alu_in2 [31:0] $end
$var wire 4 . alu_ctrl [3:0] $end
$var wire 1 / RegWrite $end
$var wire 1 0 MemWrite $end
$var wire 1 1 MemRead $end
$var wire 1 2 Branch $end
$var wire 1 3 ALUSrc $end
$var wire 2 4 ALUOp [1:0] $end
$scope module ac $end
$var wire 3 5 funct3 [2:0] $end
$var wire 7 6 funct7 [6:0] $end
$var wire 2 7 ALUOp [1:0] $end
$var reg 4 8 alu_ctrl [3:0] $end
$upscope $end
$scope module alu0 $end
$var wire 4 9 alu_control [3:0] $end
$var wire 32 : b [31:0] $end
$var wire 1 # zero $end
$var wire 32 ; a [31:0] $end
$var reg 32 < result [31:0] $end
$upscope $end
$scope module cu $end
$var wire 7 = opcode [6:0] $end
$var reg 2 > ALUOp [1:0] $end
$var reg 1 3 ALUSrc $end
$var reg 1 2 Branch $end
$var reg 1 1 MemRead $end
$var reg 1 0 MemWrite $end
$var reg 1 / RegWrite $end
$upscope $end
$scope module dm $end
$var wire 32 ? addr [31:0] $end
$var wire 1 ! clk $end
$var wire 1 1 memRead $end
$var wire 1 0 memWrite $end
$var wire 32 @ writeData [31:0] $end
$var wire 32 A readData [31:0] $end
$upscope $end
$scope module ig $end
$var wire 32 B instr [31:0] $end
$var reg 32 C imm [31:0] $end
$upscope $end
$scope module im $end
$var wire 32 D instruction [31:0] $end
$var wire 32 E addr [31:0] $end
$upscope $end
$scope module pc0 $end
$var wire 1 ! clk $end
$var wire 32 F next_pc [31:0] $end
$var wire 1 " reset $end
$var reg 32 G pc_out [31:0] $end
$upscope $end
$scope module rf $end
$var wire 1 ! clk $end
$var wire 5 H rd [4:0] $end
$var wire 32 I readData1 [31:0] $end
$var wire 32 J readData2 [31:0] $end
$var wire 1 / regWrite $end
$var wire 5 K rs1 [4:0] $end
$var wire 5 L rs2 [4:0] $end
$var wire 32 M writeData [31:0] $end
$upscope $end
$upscope $end
$upscope $end
$enddefinitions $end
#0
$dumpvars
bx M
b0 L
b0 K
bx J
bx I
b0 H
b0 G
b100 F
b0 E
b0 D
b0 C
b0 B
b0 A
bx @
bx ?
b0 >
b0 =
bx <
bx ;
bx :
b10 9
b10 8
b0 7
b0 6
b0 5
b0 4
03
02
01
00
0/
b10 .
bx -
bx ,
b0 +
b0 *
b0 )
b100 (
b0 '
bx &
bx %
bx $
x#
1"
0!
$end
#5
1!
#10
0!
0"
#15
b1000 (
b1000 F
b100 '
b100 E
b100 G
1!
#20
0!
#25
b1100 (
b1100 F
b1000 '
b1000 E
b1000 G
1!
#30
0!
#35
b10000 (
b10000 F
b1100 '
b1100 E
b1100 G
1!
#40
0!
#45
b10100 (
b10100 F
b10000 '
b10000 E
b10000 G
1!
#50
0!
#55
b11000 (
b11000 F
b10100 '
b10100 E
b10100 G
1!
#60
0!
#65
b11100 (
b11100 F
b11000 '
b11000 E
b11000 G
1!
#70
0!
#75
b100000 (
b100000 F
b11100 '
b11100 E
b11100 G
1!
#80
0!
#85
b100100 (
b100100 F
b100000 '
b100000 E
b100000 G
1!
#90
0!
#95
b101000 (
b101000 F
b100100 '
b100100 E
b100100 G
1!
#100
0!
#105
b101100 (
b101100 F
b101000 '
b101000 E
b101000 G
1!
#110
0!
#115
b110000 (
b110000 F
b101100 '
b101100 E
b101100 G
1!
#120
0!
#125
b110100 (
b110100 F
b110000 '
b110000 E
b110000 G
1!
#130
0!
#135
b111000 (
b111000 F
b110100 '
b110100 E
b110100 G
1!
#140
0!
#145
b111100 (
b111100 F
b111000 '
b111000 E
b111000 G
1!
#150
0!
#155
b1000000 (
b1000000 F
b111100 '
b111100 E
b111100 G
1!
#160
0!
#165
b1000100 (
b1000100 F
b1000000 '
b1000000 E
b1000000 G
1!
#170
0!
#175
b1001000 (
b1001000 F
b1000100 '
b1000100 E
b1000100 G
1!
#180
0!
#185
b1001100 (
b1001100 F
b1001000 '
b1001000 E
b1001000 G
1!
#190
0!
#195
b1010000 (
b1010000 F
b1001100 '
b1001100 E
b1001100 G
1!
#200
0!
#205
b1010100 (
b1010100 F
b1010000 '
b1010000 E
b1010000 G
1!
